[{"place_id": 304090272, "licence": "Data \u00a9 OpenStreetMap contributors, ODbL 1.0. https://osm.org/copyright", "osm_type": "way", "osm_id": 12187674, "boundingbox": ["39.933213061224", "39.933313061224", "-75.183144204082", "-75.183044204082"], "lat": "39.93326306122449", "lon": "-75.18309420408164", "display_name": "2305, Greenwich Street, Point Breeze, South Philadelphia, Philadelphia, Philadelphia County, Pennsylvania, 19146, United States", "class": "place", "type": "house", "importance": -0.73}]