[{"place_id": 304121979, "licence": "Data \u00a9 OpenStreetMap contributors, ODbL 1.0. https://osm.org/copyright", "osm_type": "way", "osm_id": 12155447, "boundingbox": ["39.930820897959", "39.930920897959", "-75.177111816327", "-75.177011816327"], "lat": "39.93087089795918", "lon": "-75.17706181632653", "display_name": "1933, Mountain Street, Point Breeze, South Philadelphia, Philadelphia, Philadelphia County, Pennsylvania, 19145, United States", "class": "place", "type": "house", "importance": -0.73}]