[{"place_id": 304136677, "licence": "Data \u00a9 OpenStreetMap contributors, ODbL 1.0. https://osm.org/copyright", "osm_type": "way", "osm_id": 196393959, "boundingbox": ["39.930812128205", "39.930912128205", "-75.152830641026", "-75.152730641026"], "lat": "39.93086212820513", "lon": "-75.15278064102564", "display_name": "430, Reed Street, Pennsport, South Philadelphia, Philadelphia, Philadelphia County, Pennsylvania, 19147, United States", "class": "place", "type": "house", "importance": -0.74}]