[{"place_id": 304113887, "licence": "Data \u00a9 OpenStreetMap contributors, ODbL 1.0. https://osm.org/copyright", "osm_type": "way", "osm_id": 12178257, "boundingbox": ["40.04234611955", "40.04244611955", "-75.178624906373", "-75.178524906373"], "lat": "40.04239611955034", "lon": "-75.17857490637257", "display_name": "50, East Pastorius Street, Germantown, Philadelphia, Philadelphia County, Pennsylvania, 19144, United States", "class": "place", "type": "house", "importance": -0.5299999999999999}]