[{"place_id": 70694586, "licence": "Data \u00a9 OpenStreetMap contributors, ODbL 1.0. https://osm.org/copyright", "osm_type": "node", "osm_id": 6672830110, "boundingbox": ["35.3217302", "35.3218302", "-78.6371244", "-78.6370244"], "lat": "35.3217802", "lon": "-78.6370744", "display_name": "Pizza Hut, 2302, West Cumberland Street, Dunn, Harnett County, North Carolina, 28334, United States", "class": "amenity", "type": "restaurant", "importance": 0.41009999999999996, "icon": "https://nominatim.openstreetmap.org/ui/mapicons/food_restaurant.p.20.png"}]